simpler_core/cardinality.py
simpler_core/dot.py
simpler_core/owl2jsonschema.py
simpler_core/plugin.py
simpler_core/rdf.py
simpler_core/schema.py
simpler_core/storage.py
simpler_core-0.2.0.dist-info/METADATA
simpler_core-0.2.0.dist-info/WHEEL
simpler_core-0.2.0.dist-info/top_level.txt
simpler_core-0.2.0.dist-info/RECORD
