Metadata-Version: 2.1
Name: simpler-core
Version: 0.2.0
Summary: Core library functions for adding new simpler conversion modules
Author-email: Philipp Schmurr <philipp.schmurr@kit.edu>
Maintainer-email: Philipp Schmurr <philipp.schmurr@kit.edu>
Project-URL: Homepage, https://github.com/Cpprentice/FAIRlead-model-extraction
Project-URL: Bug Reports, https://github.com/Cpprentice/FAIRlead-model-extraction/issues
Project-URL: Source, https://github.com/Cpprentice/FAIRlead-model-extraction
Keywords: entity-relationship-model,ER,extraction,model,simpler
Classifier: Development Status :: 3 - Alpha
Classifier: Intended Audience :: Developers
Classifier: License :: OSI Approved :: MIT License
Classifier: Programming Language :: Python :: 3
Classifier: Programming Language :: Python :: 3.12
Classifier: Programming Language :: Python :: 3 :: Only
Requires-Python: >=3.12
Requires-Dist: pydot ~=2.0.0
Requires-Dist: simpler-model ==0.2.2
Requires-Dist: PyYAML ~=6.0.1
Requires-Dist: networkx ~=3.3
Requires-Dist: owlready2 ~=0.46
Provides-Extra: test
Requires-Dist: pytest ; extra == 'test'
Requires-Dist: pytest-mock ; extra == 'test'
Requires-Dist: coverage ; extra == 'test'
